
<soda>
	<script file='tests/modules/teams/module_lib/setup-teams.xml'/>
	<script file='tests/modules/teams/Teams_0604.xml'/><!--Create Team Notices-->
	<script file='tests/modules/teams/Teams_9103.xml'/><!--Delete Multiple Teams-->
	<script file='tests/modules/teams/Teams_9404.xml'/><!--Mass Update-->
	<script file='tests/modules/teams/Teams_9428.xml'/><!--No Primary Team Specified-->
	<script file='tests/modules/teams/Teams_9442.xml'/><!--Select Multiple Teams And Remove Them-->
	<script file='tests/modules/teams/Teams_9461.xml'/><!--Create Record In Subpanel-->
	<script file='tests/modules/teams/Teams_9476.xml'/><!--Team Selection In Lead Convert-->
	<script file='tests/modules/teams/Teams_9522.xml'/><!--Delete Record-->
	<script file='tests/modules/teams/module_lib/cleanup-teams.xml'/>
</soda>
